hamlpy/__init__.py
hamlpy/apps.py
hamlpy/compiler.py
hamlpy/hamlpy_watcher.py
hamlpy/jinja.py
hamlpy/parser/__init__.py
hamlpy/parser/attributes.py
hamlpy/parser/core.py
hamlpy/parser/elements.py
hamlpy/parser/filters.py
hamlpy/parser/nodes.py
hamlpy/parser/utils.py
hamlpy/template/__init__.py
hamlpy/template/loaders.py
hamlpy/template/templatize.py
hamlpy/template/utils.py
hamlpy/test/__init__.py
hamlpy/test/settings.py
hamlpy/test/templates/allIfTypesTest.hamlpy
hamlpy/test/templates/allIfTypesTest.html
hamlpy/test/templates/classIdMixtures.hamlpy
hamlpy/test/templates/classIdMixtures.html
hamlpy/test/templates/djangoBase.hamlpy
hamlpy/test/templates/djangoBase.html
hamlpy/test/templates/djangoCombo.hamlpy
hamlpy/test/templates/djangoCombo.html
hamlpy/test/templates/filterMultilineIgnore.hamlpy
hamlpy/test/templates/filterMultilineIgnore.html
hamlpy/test/templates/filters.hamlpy
hamlpy/test/templates/filters.html
hamlpy/test/templates/filtersMarkdown.hamlpy
hamlpy/test/templates/filtersMarkdown.html
hamlpy/test/templates/filtersPygments.hamlpy
hamlpy/test/templates/filtersPygments.html
hamlpy/test/templates/hamlComments.hamlpy
hamlpy/test/templates/hamlComments.html
hamlpy/test/templates/implicitDivs.hamlpy
hamlpy/test/templates/implicitDivs.html
hamlpy/test/templates/multiLineDict.hamlpy
hamlpy/test/templates/multiLineDict.html
hamlpy/test/templates/nestedComments.hamlpy
hamlpy/test/templates/nestedComments.html
hamlpy/test/templates/nestedDjangoTags.hamlpy
hamlpy/test/templates/nestedDjangoTags.html
hamlpy/test/templates/nestedIfElseBlocks.hamlpy
hamlpy/test/templates/nestedIfElseBlocks.html
hamlpy/test/templates/nukeInnerWhiteSpace.hamlpy
hamlpy/test/templates/nukeInnerWhiteSpace.html
hamlpy/test/templates/nukeOuterWhiteSpace.hamlpy
hamlpy/test/templates/nukeOuterWhiteSpace.html
hamlpy/test/templates/selfClosingDjango.hamlpy
hamlpy/test/templates/selfClosingDjango.html
hamlpy/test/templates/selfClosingTags.hamlpy
hamlpy/test/templates/selfClosingTags.html
django_hamlpy-1.7.0.dist-info/LICENSE
django_hamlpy-1.7.0.dist-info/METADATA
django_hamlpy-1.7.0.dist-info/WHEEL
django_hamlpy-1.7.0.dist-info/entry_points.txt
django_hamlpy-1.7.0.dist-info/RECORD
