Metadata-Version: 2.1
Name: django-hamlpy
Version: 1.7.0
Summary: HAML like syntax for Django templates
License: MIT
Author: Nyaruka
Author-email: code@nyaruka.com
Requires-Python: >=3.9,<4.0
Classifier: Environment :: Web Environment
Classifier: Framework :: Django
Classifier: Intended Audience :: Developers
Classifier: License :: OSI Approved :: MIT License
Classifier: Operating System :: OS Independent
Classifier: Programming Language :: Python
Classifier: Programming Language :: Python :: 3
Classifier: Programming Language :: Python :: 3.9
Classifier: Programming Language :: Python :: 3.10
Classifier: Programming Language :: Python :: 3.11
Requires-Dist: django (>=3.2,<5.0)
Requires-Dist: regex (>=2020.1.1)
Project-URL: repository, http://github.com/nyaruka/django-hamlpy
